{
  "users": [
    {
      "name": "lê văn lết",
      "id": "LMeout2uT"
    },
    {
      "name": "Trương Viết Cường",
      "id": "3aGOdwB8p"
    },
    {
      "name": "tên là cường",
      "id": "ujbyxUWju"
    },
    {
      "name": "ccc",
      "id": "gnBtBwyxq"
    },
    {
      "name": "mr c",
      "phone": "0937959503",
      "id": "c6oLn3puT"
    },
    {
      "id": "FqKpxe-nz"
    },
    {
      "id": "j1wFa0suM"
    },
    {
      "id": "UZi5Tdxjb"
    },
    {
      "id": "vAzL8H5Fl"
    },
    {
      "name": "Trương Viết Cường",
      "phone": "0937959503",
      "avatar": "",
      "id": "4lgpMngeq"
    },
    {
      "name": "sdf",
      "phone": "0937959503",
      "avatar": "",
      "id": "d_nB2sPEP"
    }
  ]
}